<?xml version="1.0" encoding="UTF-8" standalone="yes"?><node artifactManager="be.nabu.eai.module.services.vm.VMServiceManager" lastModified="2016-10-20T15:45:28.542+02:00" leaf="true" version="133"><environmentId>hyperion</environmentId><properties/><references>java.lang.String</references><references>java.util.UUID</references><references>java.lang.Integer</references><references>java.lang.Boolean</references><references>be.nabu.utils.security.DigestAlgorithm</references><references>nabu.cms.core.types.model.core.User</references><references>nabu.utils.Server.uuid</references><references>nabu.cms.core.services.node.create</references><references>nabu.cms.core.database.component.selectByName</references><references>nabu.utils.Server.uuid</references><references>nabu.utils.Server.uuid</references><references>nabu.cms.core.utils.security.hashPassword</references><references>nabu.cms.core.database.user.insert</references></node>