<?xml version="1.0" encoding="UTF-8" standalone="yes"?><node artifactManager="be.nabu.eai.module.rest.provider.RESTServiceManager" lastModified="2017-06-15T13:31:42.899+02:00" leaf="true" version="8"><environmentId>hyperion</environmentId><properties/><references>nabu.services.jdbc.Services.paging</references><references>nabu.management.core.configuration</references><references>nabu.management.core.services.jdbc.pageSize</references><references>nabu.utils.reflection.Node.listByType</references><references>nabu.services.jdbc.Services.page</references><references>nabu.cms.core.management.security.types.actionList</references><references>java.lang.String</references><references>nabu.cms.core.management.security.database.action.selectAll</references><references>java.lang.Integer</references></node>