<?xml version="1.0" encoding="UTF-8" standalone="yes"?><node artifactManager="be.nabu.eai.module.services.vm.VMServiceManager" lastModified="2017-09-11T16:56:44.949+02:00" leaf="true" version="6"><environmentId>hyperion</environmentId><properties/><references>be.nabu.eai.module.auditing.api.FlatServiceTracker.track</references><references>java.util.UUID</references><references>be.nabu.eai.module.auditing.api.FlatServiceTracker$TrackType</references><references>be.nabu.libs.authentication.api.Token</references><references>be.nabu.libs.authentication.api.Device</references><references>java.lang.String</references><references>java.util.Date</references><references>java.lang.Exception</references><references>java.util.UUID</references><references>nabu.cms.core.types.model.core.NodeAudit</references><references>nabu.utils.List.reverse</references><references>nabu.cms.core.database.node.audit.selectById</references><references>nabu.utils.Server.uuid</references><references>nabu.utils.Date.now</references><references>nabu.cms.core.services.user.getCurrent</references></node>