<?xml version="1.0" encoding="UTF-8" standalone="yes"?><node artifactManager="be.nabu.eai.module.web.component.WebComponentManager" created="2018-05-22T21:02:29.132+02:00" lastModified="2020-04-26T15:56:38.081+02:00" leaf="true" version="17"><environmentId>apollo</environmentId><hidden>false</hidden><properties/><references>nabu.cms.core.manage.masterdata.rest.category.create</references><references>nabu.cms.core.manage.masterdata.rest.category.delete</references><references>nabu.cms.core.manage.masterdata.rest.category.list</references><references>nabu.cms.core.manage.masterdata.rest.category.update</references><references>nabu.cms.core.manage.masterdata.rest.entry.create</references><references>nabu.cms.core.manage.masterdata.rest.entry.delete</references><references>nabu.cms.core.manage.masterdata.rest.entry.list</references><references>nabu.cms.core.manage.masterdata.rest.entry.update</references><references>nabu.cms.core.manage.masterdata.rest.entry.get</references><references>nabu.cms.core.manage.masterdata.rest.category.get</references></node>