<?xml version="1.0" encoding="UTF-8" standalone="yes"?><node artifactManager="be.nabu.eai.module.services.vm.VMServiceManager" created="2018-08-13T15:45:31.627+02:00" lastModified="2018-08-14T09:12:47.876+02:00" leaf="true" version="21"><environmentId>hyperion</environmentId><hidden>false</hidden><properties/><references>nabu.web.application.Services.information</references><references>nabu.web.application.Services.configuration</references><references>nabu.utils.Uri.encodeUriComponent</references><references>java.lang.String</references><references>nabu.web.application.jwt.Services.marshal</references><references>nabu.utils.Date.increment</references><references>nabu.web.application.types.WebApplicationInformation</references><references>nabu.cms.core.configuration</references></node>