<?xml version="1.0" encoding="UTF-8" standalone="yes"?>
<node artifactManager="be.nabu.eai.module.web.component.WebComponentManager" deprecated="2022-10-20T16:10:29.447+02:00" lastModified="2018-01-02T10:26:46.866+01:00" leaf="true" version="10">
    <environmentId>hyperion</environmentId>
    <hidden>false</hidden>
    <properties/>
    <references>nabu.cms.core.management.translation.rest.masterdata</references>
    <references>nabu.cms.core.management.translation.rest.page.list</references>
    <references>nabu.cms.core.management.translation.rest.translation.merge</references>
    <references>nabu.cms.core.management.translation.rest.page.masterdata</references>
    <references>nabu.cms.core.management.translation.rest.translation.refresh</references>
</node>
