<structure name="user">
    <structure name="registration">
        <field name="registrationType" type="nabu.web.cms.core.model.simple.registrationType"/>
        <field name="verificationType" type="nabu.web.cms.core.model.simple.verificationType"/>
        <field comment="The service used to generate the welcome email (optionally with verificationcode). Must implement &quot;nabu.web.cms.core.specifications.welcomeEmail&quot;" minOccurs="0" name="welcomeEmailService" type="java.lang.String"/>
        <field comment="The default amount of invites that a user gets" minOccurs="0" name="amountOfInvites" type="java.lang.Integer"/>
    </structure>
    <structure name="login">
        <field comment="How often can a user fail a login before a captcha is shown?" minOccurs="0" name="maxFailsWithoutCaptcha" type="java.lang.Integer"/>
        <field comment="How many failed logins can a user have before further action is taken?" name="maxFailsTotal" type="java.lang.Integer"/>
        <field name="failedLoginAction" type="nabu.web.cms.core.model.simple.failedLoginAction"/>
        <field name="failedLoginResolution" type="nabu.web.cms.core.model.simple.failedLoginResolution"/>
        <field comment="How long (in seconds) the action taken lasts. If left open it is indefinately." minOccurs="0" name="failedLoginActionDuration" type="java.lang.Integer"/>
        <field comment="What happens if the user logs in with a new device?" minOccurs="0" name="newDevicePolicy" type="nabu.web.cms.core.model.simple.newPolicy"/>
        <field comment="What happens if the user logs in from a new geographical region?" minOccurs="0" name="newRegionPolicy" type="nabu.web.cms.core.model.simple.newPolicy"/>
        <field comment="Whether or not to allow the remember feature" name="allowRemember" type="java.lang.Boolean"/>
    </structure>
</structure>
