<?xml version="1.0" encoding="UTF-8" standalone="yes"?>
<node artifactManager="be.nabu.eai.module.services.jdbc.JDBCServiceManager" created="2022-10-20T16:13:16.647+02:00" deprecated="2024-03-26T17:30:58.337+01:00" lastModified="2023-03-16T11:10:33.421+01:00" leaf="false" version="34">
    <environmentId>apollo</environmentId>
    <hidden>false</hidden>
    <locked>false</locked>
    <properties/>
    <references>java.lang.String</references>
    <references>java.lang.Long</references>
    <references>java.lang.Integer</references>
    <references>java.lang.Boolean</references>
    <references>be.nabu.libs.services.jdbc.AffixInput</references>
    <references>nabu.cms.core.services.security.selectPermittedNodes.parameters</references>
    <references>be.nabu.libs.types.api.KeyValuePair</references>
    <references>nabu.cms.core.types.emodel.core.Node</references>
    <references>java.lang.Long</references>
    <references>java.lang.Boolean</references>
    <summary>Get all the nodes where you have the permission {parameters/action} locally</summary>
</node>
