<?xml version="1.0" encoding="UTF-8" standalone="yes"?>
<node artifactManager="be.nabu.eai.module.rest.provider.RESTServiceManager" created="2018-09-07T13:48:43.364+02:00" lastModified="2021-10-26T18:04:46.603+02:00" leaf="true" version="4">
    <environmentId>apollo</environmentId>
    <hidden>false</hidden>
    <properties/>
    <references>nabu.cms.core.manage.masterdata.rest.entry.masterDataEntry</references>
    <references>nabu.services.jdbc.utils.merge</references>
    <references>nabu.cms.core.manage.masterdata.rest.entry.masterDataEntryInput</references>
</node>
